{"data":{"Year":[2016,2017,2018,2019,2020,2016,2017,2018,2019,2020,2016,2017,2018,2019,2020],"UNIT_MEASURE":["Broj","Broj","Broj","Broj","Broj","Broj","Broj","Broj","Broj","Broj","Broj","Broj","Broj","Broj","Broj"],"Vrsta korisnika":["Ukupno","Ukupno","Ukupno","Ukupno","Ukupno","Maloljetni korisnici","Maloljetni korisnici","Maloljetni korisnici","Maloljetni korisnici","Maloljetni korisnici","Punoljetni korisnici","Punoljetni korisnici","Punoljetni korisnici","Punoljetni korisnici","Punoljetni korisnici"],"Value":[191604,184830,179164,171280,167786,53648,49035,48462,47135,41066,137956,135795,130702,124145,126720]},"edges":[]}